{
    "id_serie": 50,
    "id_tmdb": 122226,
    "seasons": [
        {
            "season_number": 1,
            "episodes": [
                {
                    "id": 46,
                    "season_number": 1,
                    "episode_number": 1,
                    "content_url": "ECMP24824/Echo%201080p%20S01E01.mkv"
                },
                {
                    "id": 47,
                    "season_number": 1,
                    "episode_number": 2,
                    "content_url": "ECMP24824/Echo%201080p%20S01E02.mkv"
                },
                {
                    "id": 48,
                    "season_number": 1,
                    "episode_number": 3,
                    "content_url": "ECMP24824/Echo%201080p%20S01E03.mkv"
                },
                {
                    "id": 49,
                    "season_number": 1,
                    "episode_number": 4,
                    "content_url": "ECMP24824/Echo%201080p%20S01E04.mkv"
                },
                {
                    "id": 50,
                    "season_number": 1,
                    "episode_number": 5,
                    "content_url": "ECMP24824/Echo%201080p%20S01E05.mkv"
                }
            ]
        }
    ]
}