{
    "content_featured": [
        {
            "content_id": 370,
            "count": 5
        },
        {
            "content_id": 379,
            "count": 3
        },
        {
            "content_id": 382,
            "count": 2
        },
        {
            "content_id": 32,
            "count": 2
        },
        {
            "content_id": 66,
            "count": 2
        },
        {
            "content_id": 345,
            "count": 2
        },
        {
            "content_id": 341,
            "count": 2
        },
        {
            "content_id": 328,
            "count": 2
        },
        {
            "content_id": 149,
            "count": 1
        },
        {
            "content_id": 391,
            "count": 1
        },
        {
            "content_id": 373,
            "count": 1
        },
        {
            "content_id": 260,
            "count": 1
        },
        {
            "content_id": 158,
            "count": 1
        },
        {
            "content_id": 12,
            "count": 1
        },
        {
            "content_id": 98,
            "count": 1
        },
        {
            "content_id": 94,
            "count": 1
        },
        {
            "content_id": 37,
            "count": 1
        },
        {
            "content_id": 36,
            "count": 1
        },
        {
            "content_id": 33,
            "count": 1
        },
        {
            "content_id": 31,
            "count": 1
        }
    ]
}