{"featured_content":[{"content_id":9,"count":11},{"content_id":208,"count":10},{"content_id":248,"count":9},{"content_id":247,"count":5},{"content_id":240,"count":5},{"content_id":64,"count":5},{"content_id":59,"count":4},{"content_id":210,"count":4},{"content_id":216,"count":4},{"content_id":202,"count":3},{"content_id":60,"count":3},{"content_id":172,"count":3},{"content_id":253,"count":3},{"content_id":260,"count":2},{"content_id":61,"count":2},{"content_id":62,"count":2},{"content_id":225,"count":2},{"content_id":65,"count":2},{"content_id":177,"count":2},{"content_id":180,"count":2}]}