{"featured_content": [{"content_id": 208, "count": 11}, {"content_id": 80, "count": 10}, {"content_id": 55, "count": 7}, {"content_id": 292, "count": 6}, {"content_id": 4, "count": 4}, {"content_id": 283, "count": 4}, {"content_id": 271, "count": 3}, {"content_id": 103, "count": 2}, {"content_id": 146, "count": 2}, {"content_id": 164, "count": 2}, {"content_id": 165, "count": 2}, {"content_id": 76, "count": 2}, {"content_id": 68, "count": 2}, {"content_id": 67, "count": 2}, {"content_id": 49, "count": 2}, {"content_id": 35, "count": 2}, {"content_id": 28, "count": 2}, {"content_id": 38, "count": 1}, {"content_id": 100, "count": 1}, {"content_id": 34, "count": 1}]}